odoo/addons/budget_plan_detail_advance_clearing/README.rst
odoo/addons/budget_plan_detail_advance_clearing/__init__.py
odoo/addons/budget_plan_detail_advance_clearing/__manifest__.py
odoo/addons/budget_plan_detail_advance_clearing/hooks.py
odoo/addons/budget_plan_detail_advance_clearing/models/__init__.py
odoo/addons/budget_plan_detail_advance_clearing/models/hr_expense.py
odoo/addons/budget_plan_detail_advance_clearing/readme/CONTRIBUTORS.md
odoo/addons/budget_plan_detail_advance_clearing/readme/DESCRIPTION.md
odoo/addons/budget_plan_detail_advance_clearing/report/__init__.py
odoo/addons/budget_plan_detail_advance_clearing/report/budget_source_fund_report.py
odoo/addons/budget_plan_detail_advance_clearing/static/description/icon.png
odoo/addons/budget_plan_detail_advance_clearing/static/description/index.html
odoo/addons/budget_plan_detail_advance_clearing/tests/__init__.py
odoo/addons/budget_plan_detail_advance_clearing/tests/test_budget_plan_detail_advance.py
odoo/addons/budget_plan_detail_advance_clearing/views/advance_budget_move.xml
odoo_addon_budget_plan_detail_advance_clearing-18.0.1.1.3.dist-info/METADATA
odoo_addon_budget_plan_detail_advance_clearing-18.0.1.1.3.dist-info/WHEEL
odoo_addon_budget_plan_detail_advance_clearing-18.0.1.1.3.dist-info/top_level.txt
odoo_addon_budget_plan_detail_advance_clearing-18.0.1.1.3.dist-info/RECORD
